pidmanager/__init__.py
pidmanager/pidmanager.py
pidmanager-1.5.dist-info/LICENSE
pidmanager-1.5.dist-info/METADATA
pidmanager-1.5.dist-info/WHEEL
pidmanager-1.5.dist-info/top_level.txt
pidmanager-1.5.dist-info/RECORD
